login_phone/__init__.py
login_phone/admin.py
login_phone/apps.py
login_phone/models.py
login_phone/tests.py
login_phone/views.py
login_phone/migrations/__init__.py
django_login_phone-0.0.1.dist-info/LICENSE
django_login_phone-0.0.1.dist-info/METADATA
django_login_phone-0.0.1.dist-info/WHEEL
django_login_phone-0.0.1.dist-info/top_level.txt
django_login_phone-0.0.1.dist-info/RECORD
