Metadata-Version: 2.1
Name: django-login-phone
Version: 0.0.1
Summary: OTP authentication
Home-page: https://github.com/SepehrHasanabadi/login_phone
Author: Sepehr Hasanabadi
Author-email: mse.hasanabadi@gmail.com
License: UNKNOWN
Platform: UNKNOWN
Classifier: Programming Language :: Python :: 3
Classifier: License :: OSI Approved :: MIT License
Classifier: Operating System :: OS Independent
Requires-Python: >=3.6
